django_template_shortcodes-0.0.3.dist-info/DESCRIPTION.rst
django_template_shortcodes-0.0.3.dist-info/METADATA
django_template_shortcodes-0.0.3.dist-info/metadata.json
django_template_shortcodes-0.0.3.dist-info/RECORD
django_template_shortcodes-0.0.3.dist-info/top_level.txt
django_template_shortcodes-0.0.3.dist-info/WHEEL
shortcodes/__init__.py
shortcodes/parser.py
shortcodes/parsers/__init__.py
shortcodes/parsers/caption.py
shortcodes/parsers/gmaps.py
shortcodes/parsers/iframe.py
shortcodes/parsers/vimeo.py
shortcodes/parsers/youtube.py
shortcodes/templatetags/__init__.py
shortcodes/templatetags/shortcode_filters.py
