Metadata-Version: 2.0
Name: django-template-shortcodes
Version: 0.0.3
Summary: Limited WordPress shortcode support for Django
Home-page: https://github.com/emilbjorklund/django-template-shortcodes
Author: Emil Björklund
Author-email: bjorklund.emil@gmail.com
License: MIT
Download-URL: https://github.com/emilbjorklund/django-template-shortcodes/archive/0.0.3.tar.gz
Platform: UNKNOWN
Classifier: Development Status :: 2 - Pre-Alpha
Classifier: Framework :: Django
Classifier: Intended Audience :: Developers
Classifier: License :: OSI Approved :: MIT License
Classifier: Programming Language :: Python :: 2.7
Requires-Dist: beautifulsoup4 (>=4.0.0)
